pylogfunctionusage/__init__.py
pylogfunctionusage/pylogfunctionusage.py
pylogfunctionusage-0.1.1.dist-info/METADATA
pylogfunctionusage-0.1.1.dist-info/WHEEL
pylogfunctionusage-0.1.1.dist-info/licenses/LICENSE.txt
pylogfunctionusage-0.1.1.dist-info/RECORD
