Metadata-Version: 2.3
Name: pylogfunctionusage
Version: 0.1.1
Summary: LogFunctionUsage in pylogfunctionusage is a Python decorator designed to enhance the logging capabilities of your functions by wrapping them in a try: block. It logs function usage, including calls, exceptions, and results, to an SQLite table
Project-URL: Homepage, https://github.com/Ambroise-D/pylogfunctionusage
Project-URL: Issues, https://github.com/Ambroise-D/pylogfunctionusage/issues
Author: Ambroise Dobosz
Maintainer: Ambroise Dobosz
License: Copyright (c) 2024 Ambroise Dobosz
License-File: LICENSE.txt
Keywords: LogFunctionUsage,logging,monitoring,pylogfunctionusage,sql,sqlite
Classifier: License :: OSI Approved :: MIT License
Classifier: Operating System :: OS Independent
Classifier: Programming Language :: Python :: 3
Requires-Python: >=3.6
